typedparse/__init__.py
typedparse/argparse.py
typedparse/parser.py
typedparse/spec.py
typedparse-0.3.dist-info/LICENSE
typedparse-0.3.dist-info/METADATA
typedparse-0.3.dist-info/WHEEL
typedparse-0.3.dist-info/top_level.txt
typedparse-0.3.dist-info/RECORD
