Metadata-Version: 2.1
Name: typedparse
Version: 0.3
Summary: Parser for command-line options based on type hints
Home-page: https://github.com/khud/typedparse
Author: Vitaly Khudobakhshov
Author-email: vitaly.khudobakhshov@gmail.com
License: Apache License 2.0
Platform: UNKNOWN
Classifier: Development Status :: 3 - Alpha
Classifier: Environment :: Console
Classifier: Topic :: Software Development :: Libraries
Classifier: License :: OSI Approved :: Apache Software License
Classifier: Programming Language :: Python :: 3
Requires-Dist: docstring-parser
